bugsnag_asgi/__init__.py
bugsnag_asgi/_version.py
bugsnag_asgi/middleware.py
bugsnag_asgi-0.2.0.dist-info/METADATA
bugsnag_asgi-0.2.0.dist-info/WHEEL
bugsnag_asgi-0.2.0.dist-info/top_level.txt
bugsnag_asgi-0.2.0.dist-info/RECORD
